{
  "post": {
    "title": "First look at Asus ROG Ally 2 and Microsoft's Project Kennan handheld | The rumored portable Xbox could launch as soon as this month",
    "author": "chrisdh79",
    "id": "1khdvca",
    "score": 65,
    "created_utc": 1746666578.0,
    "selftext": "",
    "num_comments": 26,
    "subreddit": "gadgets",
    "url": "https://www.reddit.com/r/gadgets/comments/1khdvca/first_look_at_asus_rog_ally_2_and_microsofts/"
  },
  "comments": [
    {
      "id": "mr6mxrg",
      "author": "BlastMyLoad",
      "body": "Kinda ugly looking but maybe more comfortable than the regular Ally",
      "score": 19,
      "created_utc": 1746673624.0,
      "replies": [
        {
          "id": "mr6pato",
          "author": "Special_Meaning8006",
          "body": "\ud83d\ude10",
          "score": -1,
          "created_utc": 1746674585.0,
          "replies": []
        }
      ]
    },
    {
      "id": "mr6qxix",
      "author": "antisp1n",
      "body": "This is not the portable Xbox. This is just an Xbox branded Ally 2. Portable Xbox is another project.",
      "score": 26,
      "created_utc": 1746675257.0,
      "replies": [
        {
          "id": "mr7sb4c",
          "author": "Will2LiveFading",
          "body": "The Xbox version seems to be considerably more powerful than the stock Ally 2. \n\nFrom the article, \"The listing also reveals some of the specs, which include a 7-inch, 120Hz LCD display, an 8-core, 36W AMD Ryzen Z2 Extreme CPU in the Xbox version, and a 4-core, 20W chip in the regular ROG Ally 2. They're likely running full versions of Windows 11, too, and the molded grips are thicker than those in the original ROG Ally",
          "score": 9,
          "created_utc": 1746696106.0,
          "replies": []
        },
        {
          "id": "mr9r79q",
          "author": "zadye",
          "body": "and what is your source on this?\n\nthe seems alot mere possible that they have partnered with asus to show off the possible market interrest of a full MS handheld",
          "score": -1,
          "created_utc": 1746722183.0,
          "replies": [
            {
              "id": "mrdiadj",
              "author": "fiftyshadesofseth",
              "body": "i dont have the exact quote but i know that phil xbox guy has stated that he wants to make an xbox handheld. I'm p sure that this iteration is just a partnership with Xbox's Game pass. Which would explain the xbox button, im assuming that pressing it will take you the xbox game pass menu or whatever.",
              "score": 0,
              "created_utc": 1746769373.0,
              "replies": []
            }
          ]
        },
        {
          "id": "mr8r76a",
          "author": "Small_Editor_3693",
          "body": "You have some insider info?",
          "score": -3,
          "created_utc": 1746711453.0,
          "replies": []
        }
      ]
    },
    {
      "id": "mr9aelo",
      "author": "WALL-G",
      "body": "And I bought an Ally X 2 weeks ago.\n\n\nAt least it was 2nd hand.",
      "score": 3,
      "created_utc": 1746717271.0,
      "replies": []
    },
    {
      "id": "mrszroy",
      "author": "Inevitable_Talk4627",
      "body": "Looks like it was at the bottom of a closet for a year. Sheesh. Keep your gear clean folks haha.",
      "score": 2,
      "created_utc": 1746995236.0,
      "replies": []
    },
    {
      "id": "mr63ufl",
      "author": "Marcysdad",
      "body": "How do these specs compare to the specs of the Switch 2?",
      "score": 6,
      "created_utc": 1746666796.0,
      "replies": [
        {
          "id": "mr9t6vc",
          "author": "hobx",
          "body": "More powerful but keep in mind Switch games\nwill be optimised for the specific hardware. So basically you\u2019re probably looking at similar experiences. This has a larger battery so will probably have more than the two hour playtime the swiich 2 gets.",
          "score": 8,
          "created_utc": 1746722765.0,
          "replies": [
            {
              "id": "mr9u2k4",
              "author": "Marcysdad",
              "body": "Thanks for giving me the info. That's all I wanted",
              "score": 4,
              "created_utc": 1746723019.0,
              "replies": [
                {
                  "id": "mr9umab",
                  "author": "hobx",
                  "body": "You\u2019re welcome",
                  "score": 3,
                  "created_utc": 1746723177.0,
                  "replies": []
                }
              ]
            }
          ]
        },
        {
          "id": "mr8vq0r",
          "author": "SaveHogwarts",
          "body": "I\u2019ve got no horse in the race, but why does that matter?\n\nApples and oranges when you factor in what each handheld is trying to accomplish. \n\nNot trying to be a dick, genuinely curious",
          "score": -1,
          "created_utc": 1746712888.0,
          "replies": [
            {
              "id": "mr92ffc",
              "author": "Marcysdad",
              "body": "I was asking a question without sarcasm or wanting to offend anyone.\n\nJust a comparison of these specs to a switch 2\n\n\nWhy is everyone so touchy nowadays?",
              "score": 3,
              "created_utc": 1746714921.0,
              "replies": [
                {
                  "id": "mr99tbr",
                  "author": "heavyonthehotsauce",
                  "body": "The other guy did too, you are the soft one it seems.",
                  "score": 3,
                  "created_utc": 1746717098.0,
                  "replies": []
                },
                {
                  "id": "mr92xmq",
                  "author": "SaveHogwarts",
                  "body": "I literally just asked you a question as well, and included the fact that I\u2019m not trying to be rude, and that\u2019s your response?\n\nI was genuinely curious why you were interested in comparing the two as I\u2019m thinking of getting a switch 2.",
                  "score": 0,
                  "created_utc": 1746715071.0,
                  "replies": [
                    {
                      "id": "mr9f1qm",
                      "author": "Marcysdad",
                      "body": "Because I'm on the fence what handheld console i should buy.\n\nEspecially for games like ff7 remake or cp2077",
                      "score": 5,
                      "created_utc": 1746718622.0,
                      "replies": [
                        {
                          "id": "mrau429",
                          "author": "xanas263",
                          "body": ">Especially for games like ff7 remake or cp2077\n\nIf you want a handheld for non Nintendo games then don't buy a Nintendo console. Nintendo generally has very poor 3rd party support and is mainly going to be serviced by 1st party studios.",
                          "score": 2,
                          "created_utc": 1746733522.0,
                          "replies": [
                            {
                              "id": "mraxkpl",
                              "author": "Marcysdad",
                              "body": "Not according to the reveal.\n\nThere are a lot of 3rd party titles coming",
                              "score": -1,
                              "created_utc": 1746734536.0,
                              "replies": [
                                {
                                  "id": "mraycju",
                                  "author": "xanas263",
                                  "body": "There are always lots of 3rd parties that come out with the launch. It's not the launch window you should be caring about but year 2-8 of ownership. \n\nThe Switch 2 is already known to be significantly less powerful than the current Xbox and PS. That difference will only widen with the next gen in a few years, while the Switch 2 will be in mid cycle.",
                                  "score": 3,
                                  "created_utc": 1746734767.0,
                                  "replies": [
                                    {
                                      "id": "mrb17zm",
                                      "author": "PenguinDeluxe",
                                      "body": "I don\u2019t think that\u2019s going to be an issue this generation with sooooo many games still releasing on Xbox One and PS4. I think the Switch 2 is going to see very strong 3rd party support and for awhile too.",
                                      "score": -2,
                                      "created_utc": 1746735622.0,
                                      "replies": []
                                    }
                                  ]
                                }
                              ]
                            }
                          ]
                        },
                        {
                          "id": "mrb0zm1",
                          "author": "PenguinDeluxe",
                          "body": "If it helps, the devs of Cyberpunk have said Switch 2 is the best way to play the game portably",
                          "score": -1,
                          "created_utc": 1746735552.0,
                          "replies": []
                        }
                      ]
                    }
                  ]
                }
              ]
            }
          ]
        }
      ]
    },
    {
      "id": "mr8tono",
      "author": "TheLobst3r",
      "body": "I\u2019m surprised they skipped trackpads again.",
      "score": 3,
      "created_utc": 1746712247.0,
      "replies": [
        {
          "id": "mrmw7f3",
          "author": "silentcrs",
          "body": "The Game Pass PC library is mostly games that have console equivalents. As such, controller-only inputs are fine.",
          "score": 3,
          "created_utc": 1746905362.0,
          "replies": []
        },
        {
          "id": "ms863ww",
          "author": "StanRex",
          "body": "And OLED screen ....",
          "score": 1,
          "created_utc": 1747202859.0,
          "replies": []
        }
      ]
    }
  ]
}