{
  "post": {
    "title": "A Game Boy Speedometer, Just Because You Can",
    "author": "a_Ninja_b0y",
    "id": "1i245b9",
    "score": 247,
    "created_utc": 1736965804.0,
    "selftext": "",
    "num_comments": 15,
    "subreddit": "gadgets",
    "url": "https://www.reddit.com/r/gadgets/comments/1i245b9/a_game_boy_speedometer_just_because_you_can/"
  },
  "comments": [
    {
      "id": "m7ba4nk",
      "author": "AutoModerator",
      "body": "\nWe have a giveaway running, be sure to enter in the post linked below for your chance to win a Unihertz Jelly Max - the World\u2019s Smallest 5G Smartphone!\n\n[Click here to enter!](https://www.reddit.com/r/gadgets/comments/1hfli5p/giveaway_unihertz_jelly_max_rgadgets_win_the/)\n\n\n*I am a bot, and this action was performed automatically. Please [contact the moderators of this subreddit](/message/compose/?to=/r/gadgets) if you have any questions or concerns.*",
      "score": 1,
      "created_utc": 1736965804.0,
      "replies": []
    },
    {
      "id": "m7bm21i",
      "author": "scienceguy8",
      "body": ">Just Because You Can\n\nDo you even need a better reason than that?",
      "score": 34,
      "created_utc": 1736969211.0,
      "replies": [
        {
          "id": "m7fge78",
          "author": "duosx",
          "body": "No but it would have been better phrased \u201cjust cause\u201d",
          "score": 4,
          "created_utc": 1737022892.0,
          "replies": [
            {
              "id": "m7fnw7r",
              "author": "None",
              "body": "\u201cCuz\u201d",
              "score": 2,
              "created_utc": 1737027297.0,
              "replies": [
                {
                  "id": "m7g1a2y",
                  "author": "brassmonkeyslc",
                  "body": "I said forget about it cuh.",
                  "score": 1,
                  "created_utc": 1737033360.0,
                  "replies": []
                }
              ]
            }
          ]
        },
        {
          "id": "m82z84u",
          "author": "Friendly_Engineer_",
          "body": "Because you CAN",
          "score": 2,
          "created_utc": 1737334328.0,
          "replies": []
        }
      ]
    },
    {
      "id": "m7bn8ai",
      "author": "PabloBablo",
      "body": "I love that it's possible.\n\n\nIncredibly impractical. Hard to read, clunky looking.\u00a0\n\n\nBut it's possible, and you did. Might be the first person to ever do it!",
      "score": 14,
      "created_utc": 1736969544.0,
      "replies": [
        {
          "id": "m7ce5zi",
          "author": "ninjahunz",
          "body": "By the time you readjust the magnifier and turn on the lamps your car will be wrapped around a telephone pole",
          "score": 7,
          "created_utc": 1736977136.0,
          "replies": [
            {
              "id": "m7fnzhd",
              "author": "None",
              "body": "A day of possibilities!",
              "score": 1,
              "created_utc": 1737027344.0,
              "replies": []
            }
          ]
        }
      ]
    },
    {
      "id": "m7d24ci",
      "author": "themanfromvulcan",
      "body": "What\u2019s the average speed of an unlaiden gameboy?",
      "score": 7,
      "created_utc": 1736984479.0,
      "replies": [
        {
          "id": "m7dj8qy",
          "author": "trueum26",
          "body": "African or European?",
          "score": 5,
          "created_utc": 1736990255.0,
          "replies": []
        },
        {
          "id": "m7d92vm",
          "author": "uttyrc",
          "body": "You have to know these things when you're a king.",
          "score": 1,
          "created_utc": 1736986824.0,
          "replies": [
            {
              "id": "m7g5s7u",
              "author": "Darkskynet",
              "body": "How can you they\u2019re king? \n\n\nThey\u2019re the only one not covered in shit\u2026",
              "score": 2,
              "created_utc": 1737035032.0,
              "replies": []
            }
          ]
        }
      ]
    },
    {
      "id": "m7fxmb2",
      "author": "rogue_giant",
      "body": "*Can only observe current speed during daylight hours or while passing under streetlights.",
      "score": 2,
      "created_utc": 1737031903.0,
      "replies": []
    },
    {
      "id": "m7d2oi0",
      "author": "tylers65",
      "body": "These are all over Etsy..",
      "score": 1,
      "created_utc": 1736984668.0,
      "replies": []
    }
  ]
}